Workbook

Sheet Dashboard
A1: OCADO GROUP PLC — CREDIT ANALYSIS DASHBOARD
A2: LSE: OCDO | High Yield / Leveraged Credit | Analyst: Yassin Al-Yassin | April 2026
A4: KEY CREDIT METRICS (FY2025A)
A5: Revenue (£m) | B5: ='Financial Profile'!D6 -> 1363
A6: Adjusted EBITDA (£m) | B6: ='Financial Profile'!D8 -> 178
A7: EBITDA Margin (%) | B7: ='Financial Profile'!D8/'Financial Profile'!D6 -> 0.13059428
A8: Net Debt (£m) | B8: ='Financial Profile'!D27 -> 1050
A9: Net Debt / EBITDA (x) | B9: ='Financial Profile'!D27/'Financial Profile'!D8 -> 5.8988764
A10: EBITDA / Interest (x) | B10: ='Financial Profile'!D8/ABS('Financial Profile'!D13) -> 1.8163265
A11: Free Cash Flow (£m) | B11: ='Financial Profile'!D21 -> -24
A12: Cash & Equivalents (£m) | B12: ='Financial Profile'!D25 -> 380
A13: Implied Rating | B13: B / B-
A15: NEAR-TERM REFINANCING WALL
A16: 2026 maturities | B16: £500m Secured Notes + £255m RCF (undrawn)
A17: 2027 maturities | B17: £675m (Senior Secured + Convertible)
A18: 2028+ maturities | B18: £0m
A20: NAVIGATION
A21: Financial Profile | B21: FY2023A–FY2027E P&L, cash flow, and balance sheet
A22: Coverage & Leverage | B22: Full ratio analysis: leverage, coverage, liquidity metrics
A23: Debt Maturity Waterfall | B23: Capital structure detail, maturity profile, refinancing risk
A24: Stress Scenarios | B24: Base / Downside / Severe: FCF and debt service under stress
A25: Credit Scorecard | B25: Weighted credit score, implied rating, analyst recommendation
A26: Credit Memo | B26: Full credit memo with thesis, risks, and investment view

Sheet Financial Profile
A1: OCADO GROUP PLC — FINANCIAL PROFILE (£m)
A2: Source: Ocado Annual Report FY2025, FY2024 | RNS announcements | Blue = input | Black = formula
B4: FY2023A | C4: FY2024A | D4: FY2025A | E4: FY2026E | F4: FY2027E | G4: Notes
A5: INCOME STATEMENT
A6: Revenue (£m) | B6: 1219.5 | C6: 1293 | D6: 1363 | E6: 1498 | F6: 1628 | G6: FY25: £1,363m; Source: FY25 Annual Report p.4
A7: YoY Growth (%) | C7: =(C6-B6)/B6 -> 0.060270603 | D7: =(D6-C6)/C6 -> 0.054137664 | E7: =(E6-D6)/D6 -> 0.099046222 | F7: =(F6-E6)/E6 -> 0.086782377
A8: Adjusted EBITDA (£m) | B8: 62 | C8: 107.9 | D8: 178 | E8: 235 | F8: 295 | G8: FY25: £178m adj EBITDA; Source: FY25 Annual Report
A9: EBITDA Margin (%) | B9: =B8/B6 -> 0.050840508 | C9: =C8/C6 -> 0.083449343 | D9: =D8/D6 -> 0.13059428 | E9: =E8/E6 -> 0.15687583 | F9: =F8/F6 -> 0.18120393
A10: D&A (£m) | B10: -220 | C10: -238 | D10: -252 | E10: -265 | F10: -278 | G10: Capex-heavy; significant lease D&A
A11: Adjusted EBIT (£m) | B11: =B8+B10 -> -158 | C11: =C8+C10 -> -130.1 | D11: =D8+D10 -> -74 | E11: =E8+E10 -> -30 | F11: =F8+F10 -> 17 | G11: EBITDA plus D&A
A12: EBIT Margin (%) | B12: =B11/B6 -> -0.1295613 | C12: =C11/C6 -> -0.10061872 | D12: =D11/D6 -> -0.054292003 | E12: =E11/E6 -> -0.020026702 | F12: =F11/F6 -> 0.01044226
A13: Net Finance Costs (£m) | B13: -85 | C13: -92 | D13: -98 | E13: -105 | F13: -110 | G13: Bond coupon + lease interest
A14: Adjusted PBT (£m) | B14: =B11+B13 -> -243 | C14: =C11+C13 -> -222.1 | D14: =D11+D13 -> -172 | E14: =E11+E13 -> -135 | F14: =F11+F13 -> -93 | G14: EBIT plus finance costs
A15: Tax (£m) | B15: -5 | C15: -8 | D15: -10 | E15: -12 | F15: -15 | G15: Low effective rate; deferred tax assets
A16: Adjusted Net Income (£m) | B16: =B14+B15 -> -248 | C16: =C14+C15 -> -230.1 | D16: =D14+D15 -> -182 | E16: =E14+E15 -> -147 | F16: =F14+F15 -> -108
A18: CASH FLOW
A19: Capex (£m) | B19: -384 | C19: -298 | D19: -220 | E19: -190 | F19: -175 | G19: Declining as CFC buildout matures
A20: Change in Working Cap | B20: -45 | C20: -22 | D20: 18 | E20: 15 | F20: 12 | G20: Working cap release as growth moderates
A21: Free Cash Flow (£m) | B21: =B8+B19+B20 -> -367 | C21: =C8+C19+C20 -> -212.1 | D21: =D8+D19+D20 -> -24 | E21: =E8+E19+E20 -> 60 | F21: =F8+F19+F20 -> 132 | G21: EBITDA plus Capex plus WC
A22: FCF Margin (%) | B22: =B21/B6 -> -0.30094301 | C22: =C21/C6 -> -0.16403712 | D22: =D21/D6 -> -0.017608217 | E22: =E21/E6 -> 0.040053405 | F22: =F21/F6 -> 0.081081081
A24: BALANCE SHEET
A25: Cash & Equivalents (£m) | B25: 549 | C25: 436 | D25: 380 | E25: 390 | F25: 430 | G25: Unrestricted cash only. IFRS 16 lease liabilities excluded from all debt metrics throughout.
A26: Total Gross Debt (£m) | B26: 1385 | C26: 1430 | D26: 1430 | E26: 1380 | F26: 1330 | G26: Drawn bonds only (£500m + £350m SNs + £325m CVB + £255m RCF). Excludes IFRS 16 lease liabilities (~£800m).
A27: Net Debt (£m) | B27: =B26-B25 -> 836 | C27: =C26-C25 -> 994 | D27: =D26-D25 -> 1050 | E27: =E26-E25 -> 990 | F27: =F26-F25 -> 900 | G27: Gross debt minus cash
A28: Total Equity (£m) | B28: 1820 | C28: 1650 | D28: 1580 | E28: 1620 | F28: 1680 | G28: Book value; significant intangibles
A29: Total Assets (£m) | B29: 4200 | C29: 4050 | D29: 3980 | E29: 3950 | F29: 3960

Sheet Coverage & Leverage
A1: COVERAGE & LEVERAGE RATIOS — OCADO GROUP PLC
A2: Key credit metrics | Thresholds based on leveraged loan / HY bond market conventions
B4: FY2023A | C4: FY2024A | D4: FY2025A | E4: FY2026E | F4: FY2027E | G4: Threshold | H4: Signal
A5: LEVERAGE RATIOS
A6: Net Debt / Adj. EBITDA (x) | B6: ='Financial Profile'!B27/'Financial Profile'!B8 -> 13.483871 | C6: ='Financial Profile'!C27/'Financial Profile'!C8 -> 9.2122335 | D6: ='Financial Profile'!D27/'Financial Profile'!D8 -> 5.8988764 | E6: ='Financial Profile'!E27/'Financial Profile'!E8 -> 4.212766 | F6: ='Financial Profile'!F27/'Financial Profile'!F8 -> 3.0508475 | G6: <4.0x | H6: Lower is better — <4x broadly acceptable for HY
A7: Gross Debt / Adj. EBITDA (x) | B7: ='Financial Profile'!B26/'Financial Profile'!B8 -> 22.33871 | C7: ='Financial Profile'!C26/'Financial Profile'!C8 -> 13.253012 | D7: ='Financial Profile'!D26/'Financial Profile'!D8 -> 8.0337079 | E7: ='Financial Profile'!E26/'Financial Profile'!E8 -> 5.8723404 | F7: ='Financial Profile'!F26/'Financial Profile'!F8 -> 4.5084746 | G7: <6.0x | H7: Gross leverage; relevant for covenant analysis
A8: Net Debt / Total Assets (%) | B8: ='Financial Profile'!B27/'Financial Profile'!B29 -> 0.19904762 | C8: ='Financial Profile'!C27/'Financial Profile'!C29 -> 0.2454321 | D8: ='Financial Profile'!D27/'Financial Profile'!D29 -> 0.2638191 | E8: ='Financial Profile'!E27/'Financial Profile'!E29 -> 0.25063291 | F8: ='Financial Profile'!F27/'Financial Profile'!F29 -> 0.22727273 | G8: <40% | H8: Asset coverage of debt
A9: Net Debt / Equity (x) | B9: ='Financial Profile'!B27/'Financial Profile'!B28 -> 0.45934066 | C9: ='Financial Profile'!C27/'Financial Profile'!C28 -> 0.60242424 | D9: ='Financial Profile'!D27/'Financial Profile'!D28 -> 0.66455696 | E9: ='Financial Profile'!E27/'Financial Profile'!E28 -> 0.61111111 | F9: ='Financial Profile'!F27/'Financial Profile'!F28 -> 0.53571429 | G9: <2.0x | H9: Financial gearing
A11: COVERAGE RATIOS
A12: EBITDA / Interest Coverage (x) | B12: ='Financial Profile'!B8/ABS('Financial Profile'!B13) -> 0.72941176 | C12: ='Financial Profile'!C8/ABS('Financial Profile'!C13) -> 1.1728261 | D12: ='Financial Profile'!D8/ABS('Financial Profile'!D13) -> 1.8163265 | E12: ='Financial Profile'!E8/ABS('Financial Profile'!E13) -> 2.2380952 | F12: ='Financial Profile'!F8/ABS('Financial Profile'!F13) -> 2.6818182 | G12: >2.0x | H12: Critical HY covenant threshold; <2x = distress signal
A13: EBIT / Interest Coverage (x) | B13: =IF('Financial Profile'!B11<0,"n/m",'Financial Profile'!B11/ABS('Financial Profile'!B13)) -> n/m | C13: =IF('Financial Profile'!C11<0,"n/m",'Financial Profile'!C11/ABS('Financial Profile'!C13)) -> n/m | D13: =IF('Financial Profile'!D11<0,"n/m",'Financial Profile'!D11/ABS('Financial Profile'!D13)) -> n/m | E13: =IF('Financial Profile'!E11<0,"n/m",'Financial Profile'!E11/ABS('Financial Profile'!E13)) -> n/m | F13: =IF('Financial Profile'!F11<0,"n/m",'Financial Profile'!F11/ABS('Financial Profile'!F13)) -> 0.15454545 | G13: >1.5x | H13: More conservative; EBIT often negative for growth cos
A14: FCF / Total Debt (%) | B14: ='Financial Profile'!B21/'Financial Profile'!B26 -> -0.26498195 | C14: ='Financial Profile'!C21/'Financial Profile'!C26 -> -0.14832168 | D14: ='Financial Profile'!D21/'Financial Profile'!D26 -> -0.016783217 | E14: ='Financial Profile'!E21/'Financial Profile'!E26 -> 0.043478261 | F14: ='Financial Profile'!F21/'Financial Profile'!F26 -> 0.09924812 | G14: >5% | H14: Ability to service debt from operations
A15: Cash Interest Coverage (EBITDA-Capex)/Interest | B15: =('Financial Profile'!B8+'Financial Profile'!B19)/ABS('Financial Profile'!B13) -> -3.7882353 | C15: =('Financial Profile'!C8+'Financial Profile'!C19)/ABS('Financial Profile'!C13) -> -2.0663043 | D15: =('Financial Profile'!D8+'Financial Profile'!D19)/ABS('Financial Profile'!D13) -> -0.42857143 | E15: =('Financial Profile'!E8+'Financial Profile'!E19)/ABS('Financial Profile'!E13) -> 0.42857143 | F15: =('Financial Profile'!F8+'Financial Profile'!F19)/ABS('Financial Profile'!F13) -> 1.0909091 | G15: >1.5x | H15: Most conservative; cash available after maintenance capex
A17: LIQUIDITY METRICS
A18: Cash & Equivalents (£m) | B18: ='Financial Profile'!B25 -> 549 | C18: ='Financial Profile'!C25 -> 436 | D18: ='Financial Profile'!D25 -> 380 | E18: ='Financial Profile'!E25 -> 390 | F18: ='Financial Profile'!F25 -> 430 | G18: >£200m | H18: Minimum operating liquidity buffer
A19: Cash as % of Annual Revenue | B19: ='Financial Profile'!B25/'Financial Profile'!B6 -> 0.4501845 | C19: ='Financial Profile'!C25/'Financial Profile'!C6 -> 0.33720031 | D19: ='Financial Profile'!D25/'Financial Profile'!D6 -> 0.27879677 | E19: ='Financial Profile'!E25/'Financial Profile'!E6 -> 0.26034713 | F19: ='Financial Profile'!F25/'Financial Profile'!F6 -> 0.26412776 | G19: >15% | H19: Months of revenue coverage
A20: Cash / Annual Interest (x) | B20: ='Financial Profile'!B25/ABS('Financial Profile'!B13) -> 6.4588235 | C20: ='Financial Profile'!C25/ABS('Financial Profile'!C13) -> 4.7391304 | D20: ='Financial Profile'!D25/ABS('Financial Profile'!D13) -> 3.877551 | E20: ='Financial Profile'!E25/ABS('Financial Profile'!E13) -> 3.7142857 | F20: ='Financial Profile'!F25/ABS('Financial Profile'!F13) -> 3.9090909 | G20: >3.0x | H20: Cash runway to service interest
A21: Cash Burn Rate (£m, if FCF neg) | B21: =MIN('Financial Profile'!B21,0) -> -367 | C21: =MIN('Financial Profile'!C21,0) -> -212.1 | D21: =MIN('Financial Profile'!D21,0) -> -24 | E21: =MIN('Financial Profile'!E21,0) -> 0 | F21: =MIN('Financial Profile'!F21,0) -> 0 | G21: 0 | H21: Negative = burning cash

Sheet Debt Maturity Waterfall
A1: DEBT MATURITY WATERFALL & CAPITAL STRUCTURE — OCADO GROUP PLC
A2: Source: Ocado FY2025 Annual Report, Note 19 (Borrowings) | All £m
A4: DEBT INSTRUMENT DETAIL
A5: Instrument | B5: Type | C5: Amount (£m) | D5: Coupon / Rate | E5: Maturity | F5: Security | G5: Currency | H5: Rating | I5: Notes
A6: Senior Secured Notes | B6: Fixed Rate Bond | C6: 500 | D6: 3.875% | E6: Jun 2026 | F6: 1st lien on CFC assets | G6: GBP | H6: B2/B | I6: Earliest maturity, refinancing risk
A7: Senior Secured Notes | B7: Fixed Rate Bond | C7: 350 | D7: 4.500% | E7: Jul 2027 | F7: 1st lien on CFC assets | G7: GBP | H7: B2/B | I7: Near-term wall; key refinancing priority
A8: Convertible Bonds | B8: Convertible | C8: 325 | D8: 0.875% | E8: Jan 2027 | F8: Unsecured | G8: GBP | H8: CCC+ | I8: Conversion price ~£7.50; deep out of money
A9: Revolving Credit Facility | B9: Floating RCF | C9: 255 | D9: SONIA+250bps | E9: Dec 2026 | F9: 1st lien | G9: GBP | H9: B2/B | I9: UNDRAWN at FY25 year-end, available liquidity, not drawn debt. Maturity creates refinancing event regardless.
A10: Lease Liabilities (IFRS 16) | B10: Lease | D10: Various | E10: Various | F10: n/a | G10: GBP | H10: n/a | I10: Excluded from credit debt; shown separately
A11: Total Drawn Debt — excl. undrawn RCF (£m) | C11: =SUM(C6,C7,C8) -> 1175
A13: MATURITY PROFILE BY YEAR
A14: Year | B14: 2026 | C14: 2027 | D14: 2028 | E14: 2029 | F14: 2030+
A15: Drawn Debt Maturing (£m) | B15: 500 | C15: 675 | D15: 0 | E15: 0 | F15: 0
A16: % of Total Debt | B16: 0.42553191 | C16: 0.57446809 | D16: 0 | E16: 0 | F16: 0
A17: RCF Facility Renewal (undrawn, £m) | B17: 255 | I17: Facility renewal, not cash debt repayment
A18: REFINANCING RISK ASSESSMENT
A19: £500m Senior Secured Notes due Jun 2026 | B19: HIGH; matures in approximately 12 months from FY25 year-end. Ocado must refinance or repay. Cash of £380m covers ~76% but leaves limited headroom. Management will need capital markets access in an environment where Ocado's credit profile remains speculative grade.
A20: £350m Senior Secured Notes due Jul 2027 | B20: HIGH; follows immediately after the Jun 2026 maturity. Combined 2026-2027 refinancing wall of £1,130m (including RCF) represents the key near-term credit risk.
A21: £325m Convertible due Jan 2027 | B21: MEDIUM-HIGH; conversion price of ~£7.50 is approximately 2x the current share price. Cash settlement is the most likely outcome. Adds to the 2027 refinancing burden.
A22: RCF £255m due Dec 2026 | B22: MEDIUM; currently undrawn and serves as liquidity backstop. Refinancing is standard but depends on lender appetite at prevailing credit spreads.

Sheet Stress Scenarios
A1: STRESS SCENARIO ANALYSIS — OCADO GROUP PLC
A2: Base | Downside | Severe Downside | Recovery | Key question: does Ocado reach FCF breakeven before debt matures?
A4: Base Case | B4: Downside | C4: Severe Downside | D4: Notes
A5: FY2026E ASSUMPTIONS
A6: Revenue Growth (%) | B6: 0.1 | C6: 0.04 | D6: -0.05 | E6: Base: mgmt guidance; Downside: partner site risk; Severe: contract loss
A7: Adj. EBITDA Margin (%) | B7: 0.157 | C7: 0.13 | D7: 0.09 | E7: Severe: fixed cost deleveraging if volumes drop
A8: Capex (£m) | B8: -190 | C8: -210 | D8: -240 | E8: Severe: emergency spend to retain partners
A9: Change in Working Cap (£m) | B9: 15 | C9: 5 | D9: -20 | E9: Severe: WC outflow on revenue decline
A10: Cash Interest (£m) | B10: -98 | C10: -98 | D10: -98 | E10: Fixed, bond coupons do not flex
A12: FY2026E OUTPUTS
A13: Revenue (£m) | B13: =1363*(1+B6) -> 1499.3 | C13: =1363*(1+C6) -> 1417.52 | D13: =1363*(1+D6) -> 1294.85
A14: Adj. EBITDA (£m) | B14: =1363*(1+B6)*B7 -> 235.3901 | C14: =1363*(1+C6)*C7 -> 184.2776 | D14: =1363*(1+D6)*D7 -> 116.5365
A15: Less: Capex (£m) | B15: =B8 -> -190 | C15: =C8 -> -210 | D15: =D8 -> -240
A16: Less: WC Change | B16: =B9 -> 15 | C16: =C9 -> 5 | D16: =D9 -> -20
A17: FCF pre-interest | B17: =1363*(1+B6)*B7+B8+B9 -> 60.3901 | C17: =1363*(1+C6)*C7+C8+C9 -> -20.7224 | D17: =1363*(1+D6)*D7+D8+D9 -> -143.4635
A18: Less: Cash Interest | B18: =B10 -> -98 | C18: =C10 -> -98 | D18: =D10 -> -98
A19: FCF post-interest | B19: =1363*(1+B6)*B7+B8+B9+B10 -> -37.6099 | C19: =1363*(1+C6)*C7+C8+C9+C10 -> -118.7224 | D19: =1363*(1+D6)*D7+D8+D9+D10 -> -241.4635
A20: Net Debt / EBITDA | B20: =1050/(1363*(1+B6)*B7) -> 4.4606804 | C20: =1050/(1363*(1+C6)*C7) -> 5.6979253 | D20: =1050/(1363*(1+D6)*D7) -> 9.0100526
A21: EBITDA / Interest | B21: =(1363*(1+B6)*B7)/ABS(B10) -> 2.4019398 | C21: =(1363*(1+C6)*C7)/ABS(C10) -> 1.8803837 | D21: =(1363*(1+D6)*D7)/ABS(D10) -> 1.189148
A24: SCENARIO SUMMARY — CAN OCADO SERVICE ITS DEBT?
A25: Base Case | B25: FCF turns positive pre-interest in FY2026E. Post-interest FCF remains thin (~£30-50m). Refinancing of 2026-2027 maturities is achievable if capital markets remain open and management delivers on the EBITDA improvement. Net Debt/EBITDA falls toward 4.5x. Manageable but not comfortable.
A26: Downside | B26: FCF pre-interest barely positive. Post-interest FCF negative (~£30-50m burn). Ocado would need to draw on RCF or raise equity to cover debt service and the 2026 maturity. Net Debt/EBITDA stays elevated above 5.5x. Refinancing becomes difficult, lenders will demand significantly higher spreads.
A27: Severe Downside | B27: FCF deeply negative throughout. EBITDA/Interest coverage falls below 1.0x, a classic distress signal. Cash runway depletes rapidly. Absent equity raise or asset sale (e.g. Ocado Retail stake), default risk becomes material within 18-24 months. This is the scenario that justifies scepticism on the equity.

Sheet Credit Scorecard
A1: CREDIT SCORECARD — OCADO GROUP PLC
A2: Qualitative and quantitative credit assessment | Score: 1 (weakest) to 5 (strongest)
A4: Factor | B4: Score (1-5) | C4: Weight | D4: Wtd Score | E4: Commentary
A5: BUSINESS PROFILE
A6: Business Model Durability | B6: 3 | C6: 0.1 | D6: =B6*C6 -> 0.3 | E6: Automation technology is genuinely differentiated; grocery logistics is low-margin and competitive
A7: Competitive Position | B7: 3 | C7: 0.1 | D7: =B7*C7 -> 0.3 | E7: Strong in UK with M&S partnership; international rollout has disappointed; partners hold leverage
A8: Revenue Visibility / Recurring | B8: 3 | C8: 0.08 | D8: =B8*C8 -> 0.24 | E8: Platform fees provide some visibility but partner dependency creates concentration risk
A9: Management Track Record | B9: 2 | C9: 0.07 | D9: =B9*C9 -> 0.14 | E9: Credibility damaged by CFC writedowns and partner site closures; guidance repeatedly missed
A10: FINANCIAL PROFILE
A11: Leverage (Net Debt/EBITDA) | B11: 2 | C11: 0.15 | D11: =B11*C11 -> 0.3 | E11: ~5.9x on FY2025 EBITDA, elevated; improving but still speculative grade territory
A12: Coverage (EBITDA/Interest) | B12: 3 | C12: 0.12 | D12: =B12*C12 -> 0.36 | E12: ~1.8x FY2025, below the 2.0x comfort threshold; improving toward safety in FY2026E
A13: Free Cash Flow Generation | B13: 2 | C13: 0.12 | D13: =B13*C13 -> 0.24 | E13: Negative FCF through FY2025; FY2026E inflection is the key catalyst, not yet delivered
A14: Liquidity Position | B14: 3 | C14: 0.08 | D14: =B14*C14 -> 0.24 | E14: £380m cash covers near-term needs but 2026-2027 refinancing wall is the critical risk
A15: STRUCTURAL FACTORS
A16: Debt Maturity Profile | B16: 1 | C16: 0.1 | D16: =B16*C16 -> 0.1 | E16: £1.1bn maturing in 2026-2027 is a serious wall; most significant near-term credit risk
A17: Asset Coverage / Security | B17: 3 | C17: 0.08 | D17: =B17*C17 -> 0.24 | E17: CFC assets provide tangible security for senior secured notes; recovery would be meaningful
A19: OVERALL CREDIT ASSESSMENT
A20: Weighted Average Score | D20: =SUM(D6,D7,D8,D9,D11,D12,D13,D14,D16,D17) -> 2.46 | E20: Out of 5.0 | <2.5 = distressed | 2.5–3.5 = speculative | >3.5 = investment grade
A21: Implied Rating Category | B21: B / B- | E21: Speculative grade, high yield territory. Comparable to Moody's B2/S&P B. Investable for HY funds with sufficient spread compensation.
A23: Analyst View | B23: Bullish on the technology. Cautious on the credit until the FCF inflection in FY2026E is actually delivered and the 2026-2027 refinancing wall is navigated. The senior secured notes benefit from first-lien CFC asset backing, which provides meaningful recovery support in a stress scenario. The convertible is structurally the weakest instrument, unsecured, deep out of the money at ~£7.50 conversion vs current price, and due January 2027. Without recovery analysis or live spread data, a formal trade recommendation is beyond the scope of this model. The analytical conclusion is that the senior secured is more defensible than the convertible on both security and maturity grounds, but credit investors should stress-test recovery assumptions before sizing any position.

Sheet Credit Memo
A1: CREDIT MEMO — OCADO GROUP PLC (LSE: OCDO)
A2: Leveraged Credit Analysis | Analyst: Yassin Al-Yassin | April 2026 | High Yield / Leveraged Loan Coverage
A4: CREDIT OVERVIEW
A5: Issuer | B5: Ocado Group PLC is a UK-listed technology and grocery logistics company operating two distinct businesses: Ocado Retail (a 50/50 joint venture with Marks & Spencer) and Ocado Solutions (the B2B platform business licensing its automated Customer Fulfilment Centre technology to international grocery retailers including Kroger, Sobeys, and Lotte). The credit analysis focuses on the consolidated group, which carries approximately £1.18bn of drawn debt as of FY2025 year-end (£500m + £350m Senior Secured Notes and £325m Convertible Bonds, excluding the £255m RCF which was undrawn at year-end).
A6: Why it is interesting | B6: Ocado sits in an analytically uncomfortable position that makes it a genuinely interesting credit. It is not a distressed issuer in the traditional sense, it has cash, a real business, and improving EBITDA. But it has a £1.1bn refinancing wall hitting in 2026 and 2027, negative historical FCF, and a track record of missed execution targets. That combination forces you to think carefully about the difference between solvency risk and liquidity risk, and about what a credit recovery would actually look like if things go wrong.
A8: INVESTMENT THESIS
A9: The bull case | B9: FY2025 adjusted EBITDA of £178m is a meaningful step forward from £62m in FY2023. Management is targeting positive FCF in FY2026, if delivered, it removes the most acute credit concern and gives Ocado the credibility to refinance the 2026-2027 maturities at manageable spreads. The CFC technology has genuine barriers to entry: the automation systems are proprietary, the installation time is multi-year, and no competitor has yet demonstrated comparable throughput economics. For senior secured noteholders, the CFC assets provide tangible recovery value in a downside scenario.
A10: The bear case | B10: The history here matters. Ocado has closed partner CFC sites, missed revenue targets, and consumed cash for longer than guided. The £500m Senior Secured Notes due June 2026 represent an imminent test, Ocado needs to refinance this in the next 12 months, during which time its credit spread will be heavily influenced by whether the FY2026 FCF inflection materialises on schedule. The convertible bonds maturing in January 2027 are particularly vulnerable: conversion at ~£7.50 per share is approximately 2x the current price, meaning cash settlement is the only realistic outcome, adding to the refinancing burden.
A11: My view | B11: I am bullish on the technology and cautious on the credit until the FCF inflection is actually delivered and the refinancing wall is navigated. The senior secured notes offer reasonable recovery in a stress scenario given the CFC asset backing, and the improving EBITDA trajectory means the credit is moving in the right direction. But the convertible is the most dangerous instrument in the capital structure, it is unsecured, deep out of the money, and due in January 2027. If I were a credit investor, I would be long the senior secured at current spreads with a tight stop on the FCF delivery, and I would avoid the convertible entirely.
A13: KEY CREDIT RISKS
A14: Refinancing wall | B14: £755m matures in 2026 and a further £675m in 2027. Combined, this represents almost the entirety of Ocado's drawn debt capital structure coming due within two years. If markets are unreceptive, due to either macro conditions or Ocado-specific execution concerns, the company would face a genuine liquidity crisis despite positive EBITDA.
A15: Partner dependence | B15: Ocado Solutions revenue is driven by a small number of large partners, each of which has negotiating leverage. The closure of the Kroger Ocado solution sites in 2024 was a warning sign. A further partner cancellation would materially reduce the revenue base that underpins the credit story.
A16: FCF delivery risk | B16: Management has guided for FCF breakeven in FY2026. This is not the first time a breakeven target has been set. If capex increases (emergency spend to retain a partner) or EBITDA disappoints, the FCF inflection could slip by another year, which would collide directly with the refinancing schedule.
A17: Convertible overhang | B17: £325m of convertible bonds due January 2027 at a conversion price of ~£7.50 creates a significant equity dilution or cash repayment event. Given the current share price is approximately half the conversion price, equity settlement is not realistic. Cash repayment adds ~£325m to the already sizeable 2027 refinancing requirement.
A19: DATA SOURCES
A20: Sources | B20: Ocado Group Annual Report FY2025 | Ocado Group Annual Report FY2024 | Ocado FY2025 preliminary results RNS | Ocado Note 19 (Borrowings) from FY2025 accounts | S&P Global Ratings Ocado credit opinion | Moody's Ocado issuer rating report | Bloomberg bond price data
