Workbook

Sheet Dashboard
A1: ENTERPRISE SaaS TRADING COMPS — DASHBOARD
A2: 10-company universe | NTM multiples | Feb 2026 | Analyst: Yassin Al-Yassin
A4: PEER GROUP SUMMARY STATISTICS
A5: Peer Median EV / NTM Revenue | B5: ='Trading Comps'!R19 -> 6.0778607
A6: Peer Median EV / NTM EBITDA | B6: ='Trading Comps'!T19 -> 22.437665
A7: Peer Mean EV / NTM Revenue | B7: ='Trading Comps'!R20 -> 7.1764849
A8: Peer Mean EV / NTM EBITDA | B8: ='Trading Comps'!T20 -> 24.596604
A9: Peer Median NTM Rev Growth | B9: ='Trading Comps'!K19 -> 0
A10: Peer Median NTM EBITDA Margin | B10: ='Trading Comps'!N19 -> 0
A11: Peer Median Rule of 40 | B11: ='Trading Comps'!U19 -> 0.3715
A12: EV Range (Min → Max) NTM Rev | B12: ='Trading Comps'!R17&"x → "&'Trading Comps'!R22&"x" -> 2.1219512195122x → 14.9541984732824x
A14: NAVIGATION
A15: Trading Comps | B15: 10-company peer table with LTM/NTM financials and EV multiples
A16: Valuation Bridge | B16: Implied EV and equity value using 25th pct / median / 75th pct multiples
A17: Sector Memo | B17: Full sector note: valuation framework, key metrics, risks, observations
A20: ANALYST NOTES
A21: • All NTM figures based on Bloomberg consensus estimates as of March 2026.
A22: • UK companies (Sage, Kainos, Aveva) reported in GBP; all others in USD.
A23: • Aveva (AVV) was taken private by Schneider Electric in 2023 — figures reflect last public filings.
A24: • Rule of 40 = NTM Revenue Growth + NTM EBITDA Margin. Industry benchmark threshold is 40%.
A25: • EV multiples calculated as: EV = Market Cap + Net Debt. Net Debt = Total Debt − Cash.

Sheet Trading Comps
A1: ENTERPRISE SOFTWARE & SaaS — TRADING COMPARABLES ANALYSIS
A2: NTM consensus estimates | EV multiples on NTM basis | Source: Bloomberg consensus / Yahoo Finance / company filings | Feb 2026
A3: Blue = hardcoded input | Black = formula | All USD unless noted (Sage, Kainos, Aveva in GBP)
A5: Company | B5: Ticker | C5: Exch | D5: HQ | E5: Sub-Sector | F5: Mkt Cap (bn) | G5: Net Debt (bn) | H5: EV (bn) | I5: LTM Rev (bn) | J5: NTM Rev (bn) | K5: NTM Rev Growth | L5: LTM EBITDA | M5: NTM EBITDA | N5: NTM EBITDA Margin | O5: LTM EBIT | P5: NTM EBIT | Q5: EV / LTM Rev | R5: EV / NTM Rev | S5: EV / LTM EBITDA | T5: EV / NTM EBITDA | U5: Rule of 40 (NTM)
A6: Salesforce | B6: CRM | C6: NYSE | D6: San Francisco, US | E6: CRM / Cloud | F6: 248 | G6: 3.2 | H6: 251.2 | I6: 36 | J6: 38.1 | K6: 0.058 | L6: 9.5 | M6: 10.8 | N6: 0.284 | O6: 7.1 | P6: 8.2 | Q6: =H6/I6 -> 6.9777778 | R6: =H6/J6 -> 6.5931759 | S6: =H6/L6 -> 26.442105 | T6: =H6/M6 -> 23.259259 | U6: =K6+N6 -> 0.342
A7: ServiceNow | B7: NOW | C7: NYSE | D7: Santa Clara, US | E7: ITSM / Workflow | F7: 198 | G7: -2.1 | H7: 195.9 | I7: 10.9 | J7: 13.1 | K7: 0.202 | L7: 3.8 | M7: 4.9 | N7: 0.374 | O7: 2.9 | P7: 3.8 | Q7: =H7/I7 -> 17.972477 | R7: =H7/J7 -> 14.954198 | S7: =H7/L7 -> 51.552632 | T7: =H7/M7 -> 39.979592 | U7: =K7+N7 -> 0.576
A8: Workday | B8: WDAY | C8: NASDAQ | D8: Pleasanton, US | E8: HCM / Finance Cloud | F8: 58 | G8: -2.8 | H8: 55.2 | I8: 8 | J8: 9 | K8: 0.125 | L8: 1.8 | M8: 2.3 | N8: 0.256 | O8: 1.1 | P8: 1.6 | Q8: =H8/I8 -> 6.9 | R8: =H8/J8 -> 6.1333333 | S8: =H8/L8 -> 30.666667 | T8: =H8/M8 -> 24 | U8: =K8+N8 -> 0.381
A9: SAP SE | B9: SAP | C9: NYSE | D9: Walldorf, Germany | E9: ERP / Enterprise | F9: 238 | G9: 4.1 | H9: 242.1 | I9: 37 | J9: 40.2 | K9: 0.086 | L9: 8.9 | M9: 11.2 | N9: 0.279 | O9: 6.8 | P9: 9.1 | Q9: =H9/I9 -> 6.5432432 | R9: =H9/J9 -> 6.0223881 | S9: =H9/L9 -> 27.202247 | T9: =H9/M9 -> 21.616071 | U9: =K9+N9 -> 0.365
A10: Sage Group | B10: SGE | C10: LSE | D10: Newcastle, UK | E10: SME Accounting | F10: 11.2 | G10: 0.4 | H10: 11.6 | I10: 2.37 | J10: 2.58 | K10: 0.089 | L10: 0.62 | M10: 0.71 | N10: 0.275 | O10: 0.49 | P10: 0.57 | Q10: =H10/I10 -> 4.8945148 | R10: =H10/J10 -> 4.496124 | S10: =H10/L10 -> 18.709677 | T10: =H10/M10 -> 16.338028 | U10: =K10+N10 -> 0.364
A11: Kainos Group | B11: KNOS | C11: LSE | D11: Belfast, UK | E11: Digital Transformation | F11: 1.05 | G11: -0.18 | H11: 0.87 | I11: 0.382 | J11: 0.41 | K11: 0.074 | L11: 0.082 | M11: 0.092 | N11: 0.224 | O11: 0.071 | P11: 0.08 | Q11: =H11/I11 -> 2.2774869 | R11: =H11/J11 -> 2.1219512 | S11: =H11/L11 -> 10.609756 | T11: =H11/M11 -> 9.4565217 | U11: =K11+N11 -> 0.298
A12: Temenos | B12: TEMN | C12: SIX | D12: Geneva, Switzerland | E12: Banking Software | F12: 3.8 | G12: 0.9 | H12: 4.7 | I12: 0.89 | J12: 0.94 | K12: 0.056 | L12: 0.29 | M12: 0.33 | N12: 0.351 | O12: 0.22 | P12: 0.26 | Q12: =H12/I12 -> 5.2808989 | R12: =H12/J12 -> 5 | S12: =H12/L12 -> 16.206897 | T12: =H12/M12 -> 14.242424 | U12: =K12+N12 -> 0.407
A13: Veeva Systems | B13: VEEV | C13: NYSE | D13: Pleasanton, US | E13: Life Sciences SaaS | F13: 38 | G13: -2.2 | H13: 35.8 | I13: 2.76 | J13: 3.05 | K13: 0.105 | L13: 1.08 | M13: 1.22 | N13: 0.4 | O13: 0.94 | P13: 1.07 | Q13: =H13/I13 -> 12.971014 | R13: =H13/J13 -> 11.737705 | S13: =H13/L13 -> 33.148148 | T13: =H13/M13 -> 29.344262 | U13: =K13+N13 -> 0.505
A14: HubSpot | B14: HUBS | C14: NYSE | D14: Cambridge, US | E14: Marketing / CRM | F14: 28 | G14: -0.8 | H14: 27.2 | I14: 2.63 | J14: 3.12 | K14: 0.186 | L14: 0.42 | M14: 0.58 | N14: 0.186 | O14: 0.18 | P14: 0.31 | Q14: =H14/I14 -> 10.342205 | R14: =H14/J14 -> 8.7179487 | S14: =H14/L14 -> 64.761905 | T14: =H14/M14 -> 46.896552 | U14: =K14+N14 -> 0.372
A15: Aveva Group | B15: AVV | C15: LSE | D15: Cambridge, UK | E15: Industrial Software | F15: 9.8 | G15: 0.2 | H15: 10 | I15: 1.54 | J15: 1.67 | K15: 0.084 | L15: 0.41 | M15: 0.48 | N15: 0.287 | O15: 0.32 | P15: 0.39 | Q15: =H15/I15 -> 6.4935065 | R15: =H15/J15 -> 5.988024 | S15: =H15/L15 -> 24.390244 | T15: =H15/M15 -> 20.833333 | U15: =K15+N15 -> 0.371
A17: Minimum | Q17: =MIN(Q6:Q15) -> 2.2774869 | R17: =MIN(R6:R15) -> 2.1219512 | S17: =MIN(S6:S15) -> 10.609756 | T17: =MIN(T6:T15) -> 9.4565217 | U17: =MIN(U6:U15) -> 0.298
A18: 25th Percentile | Q18: =PERCENTILE(Q6:Q15,0.25) -> 5.5840508 | R18: =PERCENTILE(R6:R15,0.25) -> 5.247006 | S18: =PERCENTILE(S6:S15,0.25) -> 20.129819 | T18: =PERCENTILE(T6:T15,0.25) -> 17.461854 | U18: =PERCENTILE(U6:U15,0.25) -> 0.36425
A19: Median | Q19: =MEDIAN(Q6:Q15) -> 6.7216216 | R19: =MEDIAN(R6:R15) -> 6.0778607 | S19: =MEDIAN(S6:S15) -> 26.822176 | T19: =MEDIAN(T6:T15) -> 22.437665 | U19: =MEDIAN(U6:U15) -> 0.3715
A20: Mean | Q20: =AVERAGE(Q6:Q15) -> 8.0653125 | R20: =AVERAGE(R6:R15) -> 7.1764849 | S20: =AVERAGE(S6:S15) -> 30.369028 | T20: =AVERAGE(T6:T15) -> 24.596604 | U20: =AVERAGE(U6:U15) -> 0.3981
A21: 75th Percentile | Q21: =PERCENTILE(Q6:Q15,0.75) -> 9.5010984 | R21: =PERCENTILE(R6:R15,0.75) -> 8.1867555 | S21: =PERCENTILE(S6:S15,0.75) -> 32.527778 | T21: =PERCENTILE(T6:T15,0.75) -> 28.008197 | U21: =PERCENTILE(U6:U15,0.75) -> 0.4005
A22: Maximum | Q22: =MAX(Q6:Q15) -> 17.972477 | R22: =MAX(R6:R15) -> 14.954198 | S22: =MAX(S6:S15) -> 64.761905 | T22: =MAX(T6:T15) -> 46.896552 | U22: =MAX(U6:U15) -> 0.576
A25: IMPLIED VALUATION — HYPOTHETICAL TARGET COMPANY
A26: Use this section to value a target using peer multiples. Enter target financials in blue.
A27: Target Company Name | B27: [Enter Name]
A28: Target NTM Revenue (bn) | B28: 0.5
A29: Target NTM EBITDA (bn) | B29: 0.12
A30: Target NTM Rev Growth | B30: 0.15
A31: Target NTM EBITDA Margin | B31: 0.24
A32: Target Net Debt (bn) | B32: 0
A33: Target Shares Outstanding (bn) | B33: 0.1
A35: IMPLIED VALUATION SUMMARY
A36: Multiple Used | B36: Multiple Applied | C36: Implied EV (bn) | D36: Less: Net Debt (bn) | E36: Implied Equity Value (bn) | F36: Implied Price per Share
A37: EV / NTM Revenue (Median) | B37: =R19 -> 6.0778607 | C37: =B37*'Trading Comps'!B28 -> 3.0389303 | D37: =-'Trading Comps'!B32 -> 0 | E37: =C37+D37 -> 3.0389303 | F37: =E37/'Trading Comps'!B33 -> 30.389303
A38: EV / NTM EBITDA (Median) | B38: =T19 -> 22.437665 | C38: =B37*'Trading Comps'!B29 -> 0.72934328 | D38: =-'Trading Comps'!B32 -> 0 | E38: =C38+D38 -> 0.72934328 | F38: =E38/'Trading Comps'!B33 -> 7.2934328
A39: EV / NTM Revenue (25th pct) | B39: =R18 -> 5.247006 | C39: =B37*'Trading Comps'!B28 -> 3.0389303 | D39: =-'Trading Comps'!B32 -> 0 | E39: =C39+D39 -> 3.0389303 | F39: =E39/'Trading Comps'!B33 -> 30.389303
A40: EV / NTM EBITDA (25th pct) | B40: =T18 -> 17.461854 | C40: =B37*'Trading Comps'!B29 -> 0.72934328 | D40: =-'Trading Comps'!B32 -> 0 | E40: =C40+D40 -> 0.72934328 | F40: =E40/'Trading Comps'!B33 -> 7.2934328

Sheet Valuation Bridge
A1: VALUATION BRIDGE — EV/NTM REVENUE & EV/NTM EBITDA RANGES
A2: Shows implied EV range for target company across 25th pct, median, and 75th pct peer multiples
A4: EV / NTM REVENUE BRIDGE
B5: Multiple | C5: Implied EV (bn) | D5: Less: Net Debt | E5: Equity Value (bn) | F5: Price/Share
A6: 25th Percentile | B6: ='Trading Comps'!R18 -> 5.247006 | C6: =B6*'Trading Comps'!B28 -> 2.623503 | D6: =-'Trading Comps'!B32 -> 0 | E6: =C6+D6 -> 2.623503 | F6: =E6/'Trading Comps'!B33 -> 26.23503
A7: Median | B7: ='Trading Comps'!R19 -> 6.0778607 | C7: =B7*'Trading Comps'!B28 -> 3.0389303 | D7: =-'Trading Comps'!B32 -> 0 | E7: =C7+D7 -> 3.0389303 | F7: =E7/'Trading Comps'!B33 -> 30.389303
A8: Mean | B8: ='Trading Comps'!R20 -> 7.1764849 | C8: =B8*'Trading Comps'!B28 -> 3.5882424 | D8: =-'Trading Comps'!B32 -> 0 | E8: =C8+D8 -> 3.5882424 | F8: =E8/'Trading Comps'!B33 -> 35.882424
A9: 75th Percentile | B9: ='Trading Comps'!R21 -> 8.1867555 | C9: =B9*'Trading Comps'!B28 -> 4.0933778 | D9: =-'Trading Comps'!B32 -> 0 | E9: =C9+D9 -> 4.0933778 | F9: =E9/'Trading Comps'!B33 -> 40.933778
A12: EV / NTM EBITDA BRIDGE
B13: Multiple | C13: Implied EV (bn) | D13: Less: Net Debt | E13: Equity Value (bn) | F13: Price/Share
A14: 25th Percentile | B14: ='Trading Comps'!T18 -> 17.461854 | C14: =B14*'Trading Comps'!B29 -> 2.0954225 | D14: =-'Trading Comps'!B32 -> 0 | E14: =C14+D14 -> 2.0954225 | F14: =E14/'Trading Comps'!B33 -> 20.954225
A15: Median | B15: ='Trading Comps'!T19 -> 22.437665 | C15: =B15*'Trading Comps'!B29 -> 2.6925198 | D15: =-'Trading Comps'!B32 -> 0 | E15: =C15+D15 -> 2.6925198 | F15: =E15/'Trading Comps'!B33 -> 26.925198
A16: Mean | B16: ='Trading Comps'!T20 -> 24.596604 | C16: =B16*'Trading Comps'!B29 -> 2.9515925 | D16: =-'Trading Comps'!B32 -> 0 | E16: =C16+D16 -> 2.9515925 | F16: =E16/'Trading Comps'!B33 -> 29.515925
A17: 75th Percentile | B17: ='Trading Comps'!T21 -> 28.008197 | C17: =B17*'Trading Comps'!B29 -> 3.3609836 | D17: =-'Trading Comps'!B32 -> 0 | E17: =C17+D17 -> 3.3609836 | F17: =E17/'Trading Comps'!B33 -> 33.609836
A20: RULE OF 40 ANALYSIS
A21: Company | B21: Rule of 40 | C21: EV/NTM Rev | D21: Interpretation
A22: ServiceNow | B22: 0.576 | C22: 15 | D22: Premium — high growth + strong margin
A23: Veeva Systems | B23: 0.505 | C23: 11.7 | D23: Premium — best-in-class execution
A24: HubSpot | B24: 0.372 | C24: 8.7 | D24: Strong — growth investing phase
A25: Workday | B25: 0.381 | C25: 6.1 | D25: Solid — maturing, margin expanding
A26: SAP SE | B26: 0.365 | C26: 6 | D26: Solid — cloud transition complete
A27: Salesforce | B27: 0.342 | C27: 6.6 | D27: Solid — scale + efficiency focus
A28: Sage Group | B28: 0.364 | C28: 4.5 | D28: Reasonable — UK SME exposure
A29: Aveva Group | B29: 0.371 | C29: 6 | D29: Solid — industrial niche premium
A30: Temenos | B30: 0.407 | C30: 5 | D30: Good — banking vertical specialist
A31: Kainos Group | B31: 0.298 | C31: 2.1 | D31: Developing — UK mid-cap, growing
A32: Rule of 40 = NTM Revenue Growth + NTM EBITDA Margin. >40% considered premium; >60% exceptional.

Sheet Sector Memo
A1: SECTOR MEMO — ENTERPRISE SOFTWARE & SaaS COVERAGE UNIVERSE
A2: Prepared by: Yassin Al-Yassin | February 2026 | Trading Comparables Analysis
A4: SECTOR OVERVIEW
A5: Coverage Universe | B5: Ten publicly listed enterprise software and SaaS companies; Salesforce, ServiceNow, Workday, SAP, Sage, Kainos, Temenos, Veeva, HubSpot, and Aveva. The universe spans US hyperscalers and UK mid-caps deliberately, because the valuation gap between them is one of the more interesting things to analyse in this sector right now.
A6: Why this sector | B6: Enterprise SaaS is the hardest comp set to do well because the multiples only make sense if you understand what drives the spread. Two companies with identical revenue growth can trade at 5x and 15x NTM revenue. That spread is explained by net revenue retention, gross margin, addressable market, and switching costs, not just growth. Getting comfortable with that is the point of this exercise.
A8: THE UK DISCOUNT — JUSTIFIED OR LAZY?
A9: The structural argument | B9: Sage, Kainos, and Aveva all trade at a material discount to US peers on EV/NTM Revenue; roughly 2 to 6x vs 6 to 15x for the US names. The standard explanation is smaller addressable markets and lower growth, which is true. But the more important reason is structural: the UK equity market is dominated by pension funds, dividend investors, and value-oriented capital. That investor base reprices growth assets downward almost mechanically. It is not that the businesses are worse, it is that the buyers are different.
A10: My view | B10: I think the UK discount is broadly justified, but not entirely. Kainos in particular is interesting, it has genuinely high-quality revenue from Workday implementation and UK public sector contracts, a Rule of 40 score that is improving, and trades at around 2x NTM revenue. The discount there looks excessive relative to fundamentals. That said, without a re-rating catalyst, a US listing, a strategic acquirer, or a shift in UK institutional appetite toward growth, the discount is likely to persist. Valuation alone is not a thesis.
A12: SALESFORCE — THE IN-BETWEEN CASE
A13: Situation | B13: Salesforce is the most interesting name in this universe precisely because it defies easy categorisation. It is not a hypergrowth SaaS company, revenue growth is running at roughly 10 to 12 percent, which puts it firmly in the mature bracket. But it is also not a legacy software vendor. It has a dominant CRM installed base with very high switching costs, strong and expanding margins, and a distribution network that most enterprise software companies would take a decade to replicate.
A14: Valuation view | B14: At around 6.6x NTM revenue, Salesforce looks roughly fairly priced. After the sector valuation reset from 2022 to 2023, most large-cap software firms settled into the 5 to 7x forward revenue range, and Salesforce sits comfortably in that band. The market is pricing it as a mature, high-quality enterprise platform with moderate growth and some AI optionality, which is an accurate description of what it actually is.
A15: The AI question | B15: Agentforce is the most credible AI product launch in enterprise software in the last two years, and that matters because Salesforce has something most AI startups do not, enterprise data, existing workflows, and a sales force that can actually get into large companies. The AI angle adds real upside optionality. But it is not the main valuation driver today. AI contributes a small fraction of revenue and the market is right to treat it as an option rather than a core assumption. If Agentforce scales over the next two to three years, the multiple has room to expand. If it does not, the base business still supports the current price.
A17: KEY METRICS FRAMEWORK
A18: EV / NTM Revenue | B18: The primary metric for this universe. Reflects the market's willingness to pay for future growth. The range in this peer group, roughly 2x to 15x, tells you everything about how differently the market prices growth quality. ServiceNow at 15x is being rewarded for compounding above 20 percent with expanding margins. Kainos at 2x reflects both lower growth and the UK structural discount described above.
A19: Rule of 40 | B19: NTM Revenue Growth plus NTM EBITDA Margin. Above 40 percent is considered healthy; above 60 percent is exceptional. ServiceNow at 57.6 percent and Veeva at 50.5 percent are the standout performers in this universe. Worth noting the Rule of 40 has a limitation: it treats a company burning margin to buy growth identically to one growing organically with expanding margins. It is a useful screen, not a substitute for reading the financials.
A20: Net Revenue Retention | B20: Not modelled here because it requires subscription revenue disclosure not always available in public filings, but NRR is arguably the most important leading indicator for SaaS health. NRR above 120 percent means the existing customer base is expanding without new customer acquisition. Any name with NRR below 100 percent is shrinking its base, which no headline growth rate can sustainably offset.
A22: DATA SOURCES
A23: Sources | B23: Bloomberg consensus estimates for all NTM figures | Yahoo Finance for market cap and share prices | Salesforce 10-K FY2025 | ServiceNow 10-K FY2024 | SAP Annual Report 2024 | Sage Group Annual Report FY2024 | Kainos Group Annual Report FY2024 | Veeva Systems 10-K FY2025 | Workday 10-K FY2025. Aveva figures reflect last public filings prior to Schneider Electric take-private in 2023.
